ziproto/Headmap.py
ziproto/ValueType.py
ziproto/ZiProtoDecoder.py
ziproto/ZiProtoEncoder.py
ziproto/ZiProtoFormat.py
ziproto/__init__.py
ziproto-1.0.dist-info/LICENSE
ziproto-1.0.dist-info/METADATA
ziproto-1.0.dist-info/WHEEL
ziproto-1.0.dist-info/top_level.txt
ziproto-1.0.dist-info/RECORD
