Metadata-Version: 2.1
Name: ziproto
Version: 1.0
Summary: Protocol Buffer used to serialize and compress data
Home-page: https://github.com/intellivoid/ZiProto-Python/
Author: Intellivoid Technologies
Author-email: netkas@intellivoid.net
License: UNKNOWN
Platform: UNKNOWN
Requires-Python: >=3.6.0
